Workbook

Sheet Read me
A1: Beauty supply chain: inventory policy model
A3: How to use: change the blue cells on the Inputs sheet (yellow = key levers); every other number is a formula.
A4: Colours: blue = input, black = formula, green = link to another sheet.
A5: Demand per DC: mean and standard deviation of daily units, January to August 2018, from the simulation of the real Olist beauty order stream scaled to a brand-sized flow (see the project README).
A6: Line-haul lead time = 1 day of loading + distance / truck km per day, rounded up.
A7: Safety stock = z x sigma x SQRT(lead time + review period); z = NORMSINV(cycle service level).
A8: Average stock = safety stock + half a review period of demand (cycle stock) + pipeline is excluded.
A9: Twin results sheet: values copied from the Python simulation (experiments/run_all.py), not formulas.

Sheet Inputs
A1: Inputs
A3: Parameter | B3: Value | C3: Note
A4: Cycle service level | B4: 0.95 | C4: Target probability of no stockout per cycle
A5: Review period (days) | B5: 1 | C5: DCs review stock every day
A6: Demand growth vs 2018 level | B6: 0 | C6: Scenario lever: +30% tests a surge
A7: Unit value (BRL) | B7: 80 | C7: Median beauty item price in the data
A8: Holding rate per year | B8: 0.25 | C8: Assumption: cost of capital, storage, obsolescence
A9: Truck km per day | B9: 650 | C9: Assumption: full-truck line haul
A10: Regional DC fixed cost per day (BRL) | B10: 1500 | C10: Assumption: rent and staff
A13: Distribution centre | B13: Mean daily demand (units) | C13: Std daily demand (units) | D13: Line-haul distance from plant (km)
A14: São Paulo DC | B14: 1106.9 | C14: 247.4 | D14: 0
A15: Recife DC | B15: 141.7 | C15: 40.7 | D15: 2130.4

Sheet Inventory policy
A1: Order-up-to policy per DC
A3: Distribution centre | B3: Mean demand incl. growth | C3: Lead time (days) | D3: Protection period (days) | E3: z | F3: Safety stock (units) | G3: Order-up-to level S (units) | H3: Average stock (units) | I3: Days of cover | J3: Holding cost per year (BRL)
A4: =Inputs!A14 -> São Paulo DC | B4: =Inputs!B14*(1+Inputs!$B$6) -> 1106.9 | C4: =1+ROUNDUP(Inputs!D14/Inputs!$B$9,0) -> 1 | D4: =C4+Inputs!$B$5 -> 2 | E4: =NORMSINV(Inputs!$B$4) -> 1.6448536 | F4: =E4*Inputs!C14*(1+Inputs!$B$6)*SQRT(D4) -> 575.49552 | G4: =B4*D4+F4 -> 2789.2955 | H4: =F4+B4*Inputs!$B$5/2 -> 1128.9455 | I4: =IF(B4>0,H4/B4,0) -> 1.0199165 | J4: =H4*Inputs!$B$7*Inputs!$B$8 -> 22578.91
A5: =Inputs!A15 -> Recife DC | B5: =Inputs!B15*(1+Inputs!$B$6) -> 141.7 | C5: =1+ROUNDUP(Inputs!D15/Inputs!$B$9,0) -> 5 | D5: =C5+Inputs!$B$5 -> 6 | E5: =NORMSINV(Inputs!$B$4) -> 1.6448536 | F5: =E5*Inputs!C15*(1+Inputs!$B$6)*SQRT(D5) -> 163.98242 | G5: =B5*D5+F5 -> 1014.1824 | H5: =F5+B5*Inputs!$B$5/2 -> 234.83242 | I5: =IF(B5>0,H5/B5,0) -> 1.6572507 | J5: =H5*Inputs!$B$7*Inputs!$B$8 -> 4696.6484
A6: Total | F6: =SUM(F4:F5) -> 739.47794 | H6: =SUM(H4:H5) -> 1363.7779 | J6: =SUM(J4:J5) -> 27275.559

Sheet Service trade-off
A1: Safety stock and holding cost versus cycle service level (all DCs)
A3: Cycle service level | B3: z | C3: Total safety stock (units) | D3: Holding cost of safety stock (BRL/yr)
A4: 0.8 | B4: =NORMSINV(A4) -> 0.84162123 | C4: =B4*(Inputs!C14*SQRT('Inventory policy'!D4)+Inputs!C15*SQRT('Inventory policy'!D5))*(1+Inputs!$B$6) -> 378.36822 | D4: =C4*Inputs!$B$7*Inputs!$B$8 -> 7567.3644
A5: 0.85 | B5: =NORMSINV(A5) -> 1.0364334 | C5: =B5*(Inputs!C14*SQRT('Inventory policy'!D4)+Inputs!C15*SQRT('Inventory policy'!D5))*(1+Inputs!$B$6) -> 465.95005 | D5: =C5*Inputs!$B$7*Inputs!$B$8 -> 9319.001
A6: 0.9 | B6: =NORMSINV(A6) -> 1.2815516 | C6: =B6*(Inputs!C14*SQRT('Inventory policy'!D4)+Inputs!C15*SQRT('Inventory policy'!D5))*(1+Inputs!$B$6) -> 576.14799 | D6: =C6*Inputs!$B$7*Inputs!$B$8 -> 11522.96
A7: 0.95 | B7: =NORMSINV(A7) -> 1.6448536 | C7: =B7*(Inputs!C14*SQRT('Inventory policy'!D4)+Inputs!C15*SQRT('Inventory policy'!D5))*(1+Inputs!$B$6) -> 739.47794 | D7: =C7*Inputs!$B$7*Inputs!$B$8 -> 14789.559
A8: 0.975 | B8: =NORMSINV(A8) -> 1.959964 | C8: =B8*(Inputs!C14*SQRT('Inventory policy'!D4)+Inputs!C15*SQRT('Inventory policy'!D5))*(1+Inputs!$B$6) -> 881.14232 | D8: =C8*Inputs!$B$7*Inputs!$B$8 -> 17622.846
A9: 0.99 | B9: =NORMSINV(A9) -> 2.3263479 | C9: =B9*(Inputs!C14*SQRT('Inventory policy'!D4)+Inputs!C15*SQRT('Inventory policy'!D5))*(1+Inputs!$B$6) -> 1045.8578 | D9: =C9*Inputs!$B$7*Inputs!$B$8 -> 20917.155
A10: 0.995 | B10: =NORMSINV(A10) -> 2.5758293 | C10: =B10*(Inputs!C14*SQRT('Inventory policy'!D4)+Inputs!C15*SQRT('Inventory policy'!D5))*(1+Inputs!$B$6) -> 1158.0173 | D10: =C10*Inputs!$B$7*Inputs!$B$8 -> 23160.346
A11: 0.999 | B11: =NORMSINV(A11) -> 3.0902323 | C11: =B11*(Inputs!C14*SQRT('Inventory policy'!D4)+Inputs!C15*SQRT('Inventory policy'!D5))*(1+Inputs!$B$6) -> 1389.2778 | D11: =C11*Inputs!$B$7*Inputs!$B$8 -> 27785.556

Sheet Twin results
A1: Scenario results from the Python digital twin (values, not formulas)
A3: scenario | B3: dcs | C3: z | D3: fill_rate_pct | E3: otif_pct | F3: lead_p50_days | G3: lead_p90_days | H3: units | I3: days_of_cover | J3: cost_per_unit_brl | K3: holding_per_unit | L3: last_mile_per_unit | M3: dc_fixed_per_unit
A4: Baseline: one DC in São Paulo, z 1.65 | B4: São Paulo DC | C4: 1.65 | D4: 93.88 | E4: 87.48 | F4: 7.41 | G4: 19.22 | H4: 483436 | I4: 4.69 | J4: 15.18 | K4: 0.26 | L4: 14.72 | M4: 0
A5: Regional DC in Recife | B5: São Paulo DC + Recife DC | C5: 1.65 | D5: 92.13 | E5: 88.01 | F5: 7.08 | G5: 16.99 | H5: 483436 | I5: 5.21 | J5: 16.01 | K5: 0.29 | L5: 13.59 | M5: 1.77
A6: Lower safety stock, z 0.84 | B6: São Paulo DC | C6: 0.84 | D6: 93.69 | E6: 87.45 | F6: 7.42 | G6: 19.22 | H6: 483436 | I6: 4.55 | J6: 15.17 | K6: 0.25 | L6: 14.72 | M6: 0
A7: Higher safety stock, z 2.33 | B7: São Paulo DC | C7: 2.33 | D7: 93.88 | E7: 87.49 | F7: 7.41 | G7: 19.21 | H7: 483436 | I7: 4.81 | J7: 15.18 | K7: 0.26 | L7: 14.72 | M7: 0
A8: Plant capacity 1.5 x demand | B8: São Paulo DC | C8: 1.65 | D8: 95.25 | E8: 87.95 | F8: 7.31 | G8: 19.1 | H8: 483436 | I8: 4.94 | J8: 15.19 | K8: 0.27 | L8: 14.72 | M8: 0
A9: Pre-build 10 days before Black Friday | B9: São Paulo DC | C9: 1.65 | D9: 98.07 | E9: 88.4 | F9: 7.22 | G9: 18.98 | H9: 483436 | I9: 5.34 | J9: 15.21 | K9: 0.29 | L9: 14.72 | M9: 0
A10: Unplanned +40 % demand, May 2018 | B10: São Paulo DC | C10: 1.65 | D10: 89.67 | E10: 87.4 | F10: 7.47 | G10: 19.23 | H10: 498436 | I10: 4.45 | J10: 15.13 | K10: 0.24 | L10: 14.69 | M10: 0
A11: Plant at 50 % for 4 weeks, March 2018 | B11: São Paulo DC | C11: 1.65 | D11: 93.88 | E11: 87.48 | F11: 7.41 | G11: 19.22 | H11: 483436 | I11: 4.58 | J11: 15.17 | K11: 0.25 | L11: 14.72 | M11: 0
